easyphysi/__init__.py
easyphysi/utils.py
easyphysi/drivers/__init__.py
easyphysi/drivers/axes.py
easyphysi/drivers/body.py
easyphysi/drivers/equation.py
easyphysi/drivers/scalar.py
easyphysi/drivers/system.py
easyphysi/drivers/universe.py
easyphysi/drivers/vector.py
easyphysi/equations/__init__.py
easyphysi/equations/electrical_field_intensity_equation.py
easyphysi/equations/electrical_force_equation.py
easyphysi/equations/electrical_potential_energy_equation.py
easyphysi/equations/electrical_potential_equation.py
easyphysi/equations/energy_conservation_equation.py
easyphysi/equations/gravitational_field_intensity_equation.py
easyphysi/equations/gravitational_force_equation.py
easyphysi/equations/gravitational_potential_energy_equation.py
easyphysi/equations/gravitational_potential_equation.py
easyphysi/equations/linear_position_equation.py
easyphysi/equations/linear_velocity_equation.py
easyphysi/equations/newton_equation.py
easyphysi-1.0.1.dist-info/LICENSE
easyphysi-1.0.1.dist-info/METADATA
easyphysi-1.0.1.dist-info/WHEEL
easyphysi-1.0.1.dist-info/top_level.txt
easyphysi-1.0.1.dist-info/RECORD
