Metadata-Version: 2.1
Name: easyphysi
Version: 1.0.1
Summary: Physics library to solve pre-universitary physics problems
Home-page: https://github.com/girdeux31/easyPhysi
Author: Carles Mesado
Author-email: mesado31@gmail.com
Keywords: {physics,pre-university,bachiller,uarm,kinematics,dynamics,energy conservation,gravitational field,electrical field}
Platform: any
Classifier: Programming Language :: Python :: 3
Classifier: License :: OSI Approved :: GNU General Public License v3 (GPLv3)
Classifier: Operating System :: OS Independent
Requires-Python: >=3.7
License-File: LICENSE
Requires-Dist: matplotlib >=3.7.0
Requires-Dist: scipy >=1.11.0
Requires-Dist: sympy ==1.12
